main.py
listmonk_exporter-0.2.0.dist-info/licenses/LICENSE
listmonk_exporter-0.2.0.dist-info/METADATA
listmonk_exporter-0.2.0.dist-info/WHEEL
listmonk_exporter-0.2.0.dist-info/entry_points.txt
listmonk_exporter-0.2.0.dist-info/top_level.txt
listmonk_exporter-0.2.0.dist-info/RECORD
