Metadata-Version: 2.4
Name: listmonk-exporter
Version: 0.2.0
Summary: A Prometheus exporter for Listmonk newsletter and mailing list manager
Author-email: Meysam Azad <contact@meysam.io>
Maintainer-email: Meysam Azad <contact@meysam.io>
License: Apache-2.0
Project-URL: Homepage, https://github.com/meysam81/listmonk-exporter
Project-URL: Documentation, https://github.com/meysam81/listmonk-exporter#readme
Project-URL: Repository, https://github.com/meysam81/listmonk-exporter
Project-URL: Issues, https://github.com/meysam81/listmonk-exporter/issues
Project-URL: Changelog, https://github.com/meysam81/listmonk-exporter/releases
Keywords: listmonk,prometheus,exporter,monitoring,metrics,newsletter,email,mailing-list
Classifier: Development Status :: 4 - Beta
Classifier: Intended Audience :: Developers
Classifier: Intended Audience :: System Administrators
Classifier: License :: OSI Approved :: Apache Software License
Classifier: Operating System :: OS Independent
Classifier: Programming Language :: Python :: 3
Classifier: Programming Language :: Python :: 3.11
Classifier: Programming Language :: Python :: 3.12
Classifier: Programming Language :: Python :: 3.13
Classifier: Programming Language :: Python :: 3.13
Classifier: Programming Language :: Python :: 3.14
Classifier: Topic :: System :: Monitoring
Classifier: Topic :: System :: Networking :: Monitoring
Classifier: Topic :: Communications :: Email
Classifier: Topic :: Software Development :: Libraries :: Python Modules
Requires-Python: <4.0,>=3.11
License-File: LICENSE
Requires-Dist: httpx<1,>=0.27.0
Requires-Dist: prometheus-client<1,>=0.20.0
Requires-Dist: pydantic-settings<3,>=2.0.0
Requires-Dist: pydantic<3,>=2.0.0
Dynamic: license-file
